api_hunt/__init__.py
api_hunt/add_delete.py
api_hunt/cli.py
api_hunt/core.py
api_hunt/get_repattern_ai.py
api_hunt/patterns.py
api_hunter-0.1.2.dist-info/METADATA
api_hunter-0.1.2.dist-info/WHEEL
api_hunter-0.1.2.dist-info/entry_points.txt
api_hunter-0.1.2.dist-info/top_level.txt
api_hunter-0.1.2.dist-info/RECORD
